[
  {
    "employee_id": 670487.0,
    "full_name": "Patrick Sanchez",
    "department": "Product Architecture",
    "position": "Integration Specialist",
    "level": "mid",
    "hire_date": "2020-06-17",
    "city": "Berlin",
    "country": "Germany",
    "region": "EMEA",
    "remote_work_ratio": 0.65,
    "travel_percentage": 26.0,
    "base_salary": 119000.0,
    "billing_rate": 2100.0,
    "utilization_target": 75.0,
    "actual_utilization": 76.8,
    "primary_specialization": "Cloud Infrastructure",
    "secondary_specialization": "Cloud Infrastructure",
    "industry_expertise": "Enterprise Software, HealthTech",
    "certifications": "Azure Architect, TOGAF",
    "performance_score": 4.3,
    "client_satisfaction": 4.5,
    "internal_project_contribution": 5.0,
    "active_projects": 3.0,
    "project_complexity_score": 3.0,
    "delivery_quality_score": 96.3,
    "innovation_contribution": 6.9,
    "training_hours": 38.0,
    "mentorship_hours": 15.0,
    "promotion_readiness": 89.8,
    "flight_risk_score": 68.0,
    "engagement_score": 8.1,
    "knowledge_sharing_index": 6.1,
    "manager_id": 902931,
    "total_comp": 136850.0,
    "team_lead_projects": 1.0,
    "direct_reports": 0.0
  },
  {
    "employee_id": 146316.0,
    "full_name": "Megan Mcclain",
    "department": "Design & UX",
    "position": "UI Designer I",
    "level": "entry",
    "hire_date": "2023-01-22",
    "city": "Berlin",
    "country": "Germany",
    "region": "EMEA",
    "remote_work_ratio": 0.42,
    "travel_percentage": 9.0,
    "base_salary": 82000.0,
    "billing_rate": 1100.0,
    "utilization_target": 74.0,
    "actual_utilization": 65.9,
    "primary_specialization": "User Research",
    "secondary_specialization": "Service Design",
    "industry_expertise": "EdTech, FinTech",
    "certifications": "Human Factors International, Interaction Design Foundation",
    "performance_score": 3.3,
    "client_satisfaction": 4.5,
    "internal_project_contribution": 3.0,
    "active_projects": 2.0,
    "project_complexity_score": 1.0,
    "delivery_quality_score": 82.7,
    "innovation_contribution": 6.7,
    "training_hours": 49.0,
    "mentorship_hours": -28.0,
    "promotion_readiness": 74.2,
    "flight_risk_score": 26.0,
    "engagement_score": 7.3,
    "knowledge_sharing_index": 2.9,
    "manager_id": 883794,
    "total_comp": 90200.00000000001,
    "team_lead_projects": 0.0,
    "direct_reports": 0.0
  },
  {
    "employee_id": 91161.0,
    "full_name": "Amanda Davis",
    "department": "Design & UX",
    "position": "Design Lead",
    "level": "mid",
    "hire_date": "2020-01-05",
    "city": "New York",
    "country": "USA",
    "region": "Americas",
    "remote_work_ratio": 0.54,
    "travel_percentage": 18.0,
    "base_salary": 157000.0,
    "billing_rate": 1900.0,
    "utilization_target": 70.0,
    "actual_utilization": 68.4,
    "primary_specialization": "Design Thinking",
    "secondary_specialization": "Web Applications",
    "industry_expertise": "Industrial Tech, Enterprise Software",
    "certifications": "Human Factors International, Google UX Design, Interaction Design Foundation",
    "performance_score": 3.9,
    "client_satisfaction": 4.7,
    "internal_project_contribution": 3.0,
    "active_projects": 2.0,
    "project_complexity_score": 3.0,
    "delivery_quality_score": 95.9,
    "innovation_contribution": 8.6,
    "training_hours": 42.0,
    "mentorship_hours": -2.0,
    "promotion_readiness": 57.6,
    "flight_risk_score": 56.0,
    "engagement_score": 8.3,
    "knowledge_sharing_index": 4.9,
    "manager_id": 883794,
    "total_comp": 180550.0,
    "team_lead_projects": 0.0,
    "direct_reports": 0.0
  },
  {
    "employee_id": 243962.0,
    "full_name": "Alyssa Gonzalez",
    "department": "Product Strategy",
    "position": "Market Researcher",
    "level": "entry",
    "hire_date": "2022-09-19",
    "city": "New York",
    "country": "USA",
    "region": "Americas",
    "remote_work_ratio": 0.33,
    "travel_percentage": 16.0,
    "base_salary": 91000.0,
    "billing_rate": 1400.0,
    "utilization_target": 76.0,
    "actual_utilization": 73.6,
    "primary_specialization": "Market Analysis",
    "secondary_specialization": "Product Discovery",
    "industry_expertise": "Enterprise Software, HealthTech, Social Impact",
    "certifications": "Product Management (PMP), PSPO",
    "performance_score": 3.3,
    "client_satisfaction": 4.7,
    "internal_project_contribution": 1.0,
    "active_projects": 2.0,
    "project_complexity_score": 3.0,
    "delivery_quality_score": 86.9,
    "innovation_contribution": 6.2,
    "training_hours": 42.0,
    "mentorship_hours": -18.0,
    "promotion_readiness": 55.3,
    "flight_risk_score": 49.0,
    "engagement_score": 7.6,
    "knowledge_sharing_index": 3.9,
    "manager_id": 988712,
    "total_comp": 100100.00000000001,
    "team_lead_projects": 0.0,
    "direct_reports": 0.0
  },
  {
    "employee_id": 681453.0,
    "full_name": "Jennifer Cole",
    "department": "Product Architecture",
    "position": "Integration Specialist",
    "level": "mid",
    "hire_date": "2021-05-12",
    "city": "New York",
    "country": "USA",
    "region": "Americas",
    "remote_work_ratio": 0.74,
    "travel_percentage": 30.0,
    "base_salary": 126000.0,
    "billing_rate": 2100.0,
    "utilization_target": 73.0,
    "actual_utilization": 73.7,
    "primary_specialization": "API Design",
    "secondary_specialization": "Cloud Infrastructure",
    "industry_expertise": "Social Impact, Industrial Tech, HealthTech, EdTech",
    "certifications": "TOGAF, Google Cloud Architect",
    "performance_score": 3.5,
    "client_satisfaction": 4.4,
    "internal_project_contribution": 3.0,
    "active_projects": 2.0,
    "project_complexity_score": 4.0,
    "delivery_quality_score": 90.8,
    "innovation_contribution": 7.5,
    "training_hours": 47.0,
    "mentorship_hours": 20.0,
    "promotion_readiness": 86.1,
    "flight_risk_score": 53.0,
    "engagement_score": 8.3,
    "knowledge_sharing_index": 5.8,
    "manager_id": 732052,
    "total_comp": 144900.0,
    "team_lead_projects": 1.0,
    "direct_reports": 0.0
  },
  {
    "employee_id": 291704.0,
    "full_name": "Abigail Shaffer",
    "department": "Product Architecture",
    "position": "Enterprise Architect",
    "level": "mid",
    "hire_date": "2020-04-12",
    "city": "London",
    "country": "UK",
    "region": "EMEA",
    "remote_work_ratio": 0.65,
    "travel_percentage": 27.0,
    "base_salary": 147000.0,
    "billing_rate": 1600.0,
    "utilization_target": 76.0,
    "actual_utilization": 81.3,
    "primary_specialization": "Data Architecture",
    "secondary_specialization": "Microservices",
    "industry_expertise": "Industrial Tech, Social Impact",
    "certifications": "TOGAF, Google Cloud Architect",
    "performance_score": 3.9,
    "client_satisfaction": 4.7,
    "internal_project_contribution": 4.0,
    "active_projects": 2.0,
    "project_complexity_score": 3.0,
    "delivery_quality_score": 84.1,
    "innovation_contribution": 7.4,
    "training_hours": 42.0,
    "mentorship_hours": 11.0,
    "promotion_readiness": 81.0,
    "flight_risk_score": 48.0,
    "engagement_score": 8.3,
    "knowledge_sharing_index": 5.4,
    "manager_id": 604201,
    "total_comp": 169050.0,
    "team_lead_projects": 1.0,
    "direct_reports": 0.0
  },
  {
    "employee_id": 732052.0,
    "full_name": "Donald Lewis",
    "department": "Product Architecture",
    "position": "Head of Architecture",
    "level": "senior",
    "hire_date": "2018-10-08",
    "city": "New York",
    "country": "USA",
    "region": "Americas",
    "remote_work_ratio": 0.82,
    "travel_percentage": 33.0,
    "base_salary": 202000.0,
    "billing_rate": 2400.0,
    "utilization_target": 66.0,
    "actual_utilization": 69.6,
    "primary_specialization": "Cloud Infrastructure",
    "secondary_specialization": "System Integration",
    "industry_expertise": "Enterprise Software, E-commerce",
    "certifications": "Google Cloud Architect, AWS Solutions Architect, TOGAF, Azure Architect",
    "performance_score": 4.2,
    "client_satisfaction": 4.2,
    "internal_project_contribution": 7.0,
    "active_projects": 3.0,
    "project_complexity_score": 4.0,
    "delivery_quality_score": 94.8,
    "innovation_contribution": 7.6,
    "training_hours": 33.0,
    "mentorship_hours": 31.0,
    "promotion_readiness": 12.707358690597623,
    "flight_risk_score": 49.0,
    "engagement_score": 8.2,
    "knowledge_sharing_index": 7.1,
    "manager_id": null,
    "total_comp": 242400.0,
    "team_lead_projects": 2.0,
    "direct_reports": 2.0
  },
  {
    "employee_id": 800581.0,
    "full_name": "Brandon Davis",
    "department": "Product Architecture",
    "position": "Junior Solution Architect",
    "level": "entry",
    "hire_date": "2022-11-15",
    "city": "Singapore",
    "country": "Singapore",
    "region": "APAC",
    "remote_work_ratio": 0.65,
    "travel_percentage": 18.0,
    "base_salary": 83000.0,
    "billing_rate": 1100.0,
    "utilization_target": 80.0,
    "actual_utilization": 67.8,
    "primary_specialization": "Microservices",
    "secondary_specialization": "System Integration",
    "industry_expertise": "Enterprise Software, EdTech, FinTech",
    "certifications": "AWS Solutions Architect, Google Cloud Architect",
    "performance_score": 3.9,
    "client_satisfaction": 4.5,
    "internal_project_contribution": 3.0,
    "active_projects": 1.0,
    "project_complexity_score": 1.0,
    "delivery_quality_score": 83.5,
    "innovation_contribution": 6.5,
    "training_hours": 47.0,
    "mentorship_hours": -25.0,
    "promotion_readiness": 56.3,
    "flight_risk_score": 50.0,
    "engagement_score": 6.9,
    "knowledge_sharing_index": 2.8,
    "manager_id": 604201,
    "total_comp": 91300.00000000001,
    "team_lead_projects": 0.0,
    "direct_reports": 0.0
  },
  {
    "employee_id": 888662.0,
    "full_name": "Dennis Williams",
    "department": "Product Strategy",
    "position": "Product Strategist",
    "level": "mid",
    "hire_date": "2019-10-25",
    "city": "London",
    "country": "UK",
    "region": "EMEA",
    "remote_work_ratio": 0.45,
    "travel_percentage": 43.0,
    "base_salary": 131000.0,
    "billing_rate": 2000.0,
    "utilization_target": 72.0,
    "actual_utilization": 84.9,
    "primary_specialization": "Market Analysis",
    "secondary_specialization": "Product Discovery",
    "industry_expertise": "Enterprise Software, E-commerce",
    "certifications": "Product Management (PMP), PSPO",
    "performance_score": 3.4,
    "client_satisfaction": 4.6,
    "internal_project_contribution": 3.0,
    "active_projects": 3.0,
    "project_complexity_score": 4.0,
    "delivery_quality_score": 89.7,
    "innovation_contribution": 8.0,
    "training_hours": 46.0,
    "mentorship_hours": -5.0,
    "promotion_readiness": 57.3,
    "flight_risk_score": 52.0,
    "engagement_score": 6.7,
    "knowledge_sharing_index": 4.6,
    "manager_id": 442666,
    "total_comp": 150650.0,
    "team_lead_projects": 1.0,
    "direct_reports": 0.0
  },
  {
    "employee_id": 481741.0,
    "full_name": "Valerie Gray",
    "department": "Design & UX",
    "position": "UX Researcher I",
    "level": "entry",
    "hire_date": "2023-09-01",
    "city": "San Francisco",
    "country": "USA",
    "region": "Americas",
    "remote_work_ratio": 0.59,
    "travel_percentage": 11.0,
    "base_salary": 85000.0,
    "billing_rate": 1000.0,
    "utilization_target": 73.0,
    "actual_utilization": 78.1,
    "primary_specialization": "Service Design",
    "secondary_specialization": "Service Design",
    "industry_expertise": "Social Impact, HealthTech, Consumer Tech",
    "certifications": "Google UX Design, Interaction Design Foundation",
    "performance_score": 3.6,
    "client_satisfaction": 4.3,
    "internal_project_contribution": 3.0,
    "active_projects": 3.0,
    "project_complexity_score": 2.0,
    "delivery_quality_score": 92.8,
    "innovation_contribution": 6.0,
    "training_hours": 42.0,
    "mentorship_hours": -30.0,
    "promotion_readiness": 58.3,
    "flight_risk_score": 56.0,
    "engagement_score": 8.5,
    "knowledge_sharing_index": 2.1,
    "manager_id": 238968,
    "total_comp": 93500.00000000001,
    "team_lead_projects": 0.0,
    "direct_reports": 0.0
  },
  {
    "employee_id": 578856.0,
    "full_name": "Mark Mcclure",
    "department": "Engineering Delivery",
    "position": "Associate Developer",
    "level": "entry",
    "hire_date": "2023-01-09",
    "city": "London",
    "country": "UK",
    "region": "EMEA",
    "remote_work_ratio": 0.78,
    "travel_percentage": 11.0,
    "base_salary": 86000.0,
    "billing_rate": 1100.0,
    "utilization_target": 86.0,
    "actual_utilization": 79.1,
    "primary_specialization": "Cloud Native",
    "secondary_specialization": "Mobile Development",
    "industry_expertise": "FinTech, Consumer Tech, Social Impact, E-commerce",
    "certifications": "Kubernetes",
    "performance_score": 3.5,
    "client_satisfaction": 4.2,
    "internal_project_contribution": 1.0,
    "active_projects": 1.0,
    "project_complexity_score": 2.0,
    "delivery_quality_score": 75.1,
    "innovation_contribution": 5.2,
    "training_hours": 46.0,
    "mentorship_hours": -20.0,
    "promotion_readiness": 48.1,
    "flight_risk_score": 60.0,
    "engagement_score": 8.2,
    "knowledge_sharing_index": 3.0,
    "manager_id": 783300,
    "total_comp": 94600.00000000001,
    "team_lead_projects": 0.0,
    "direct_reports": 0.0
  },
  {
    "employee_id": 379201.0,
    "full_name": "Michele Williams",
    "department": "Product Architecture",
    "position": "Solution Architect",
    "level": "mid",
    "hire_date": "2018-06-12",
    "city": "Singapore",
    "country": "Singapore",
    "region": "APAC",
    "remote_work_ratio": 0.68,
    "travel_percentage": 28.0,
    "base_salary": 119000.0,
    "billing_rate": 2200.0,
    "utilization_target": 76.0,
    "actual_utilization": 70.2,
    "primary_specialization": "Security Architecture",
    "secondary_specialization": "API Design",
    "industry_expertise": "EdTech, Social Impact, FinTech, Consumer Tech",
    "certifications": "Azure Architect, TOGAF",
    "performance_score": 3.6,
    "client_satisfaction": 4.0,
    "internal_project_contribution": 4.0,
    "active_projects": 2.0,
    "project_complexity_score": 4.0,
    "delivery_quality_score": 87.9,
    "innovation_contribution": 6.3,
    "training_hours": 39.0,
    "mentorship_hours": 1.0,
    "promotion_readiness": 91.0,
    "flight_risk_score": 70.0,
    "engagement_score": 8.4,
    "knowledge_sharing_index": 4.1,
    "manager_id": 604201,
    "total_comp": 136850.0,
    "team_lead_projects": 1.0,
    "direct_reports": 0.0
  },
  {
    "employee_id": 238968.0,
    "full_name": "Victoria Wyatt",
    "department": "Design & UX",
    "position": "Chief Experience Officer",
    "level": "senior",
    "hire_date": "2017-11-07",
    "city": "New York",
    "country": "USA",
    "region": "Americas",
    "remote_work_ratio": 0.67,
    "travel_percentage": 25.0,
    "base_salary": 249000.0,
    "billing_rate": 3000.0,
    "utilization_target": 61.0,
    "actual_utilization": 83.5,
    "primary_specialization": "Web Applications",
    "secondary_specialization": "Web Applications",
    "industry_expertise": "EdTech, FinTech",
    "certifications": "Human Factors International, Interaction Design Foundation",
    "performance_score": 4.0,
    "client_satisfaction": 4.6,
    "internal_project_contribution": 7.0,
    "active_projects": 5.0,
    "project_complexity_score": 4.0,
    "delivery_quality_score": 93.8,
    "innovation_contribution": 9.1,
    "training_hours": 23.0,
    "mentorship_hours": 32.0,
    "promotion_readiness": 26.16500348718269,
    "flight_risk_score": 50.0,
    "engagement_score": 6.9,
    "knowledge_sharing_index": 8.6,
    "manager_id": null,
    "total_comp": 298800.0,
    "team_lead_projects": 1.0,
    "direct_reports": 5.0
  },
  {
    "employee_id": 908573.0,
    "full_name": "Donald Reid",
    "department": "Engineering Delivery",
    "position": "Associate Developer",
    "level": "entry",
    "hire_date": "2023-05-18",
    "city": "San Francisco",
    "country": "USA",
    "region": "Americas",
    "remote_work_ratio": 0.6,
    "travel_percentage": 4.0,
    "base_salary": 84000.0,
    "billing_rate": 1400.0,
    "utilization_target": 87.0,
    "actual_utilization": 70.6,
    "primary_specialization": "Mobile Development",
    "secondary_specialization": "Cloud Native",
    "industry_expertise": "Consumer Tech, FinTech, EdTech",
    "certifications": "Kubernetes, Azure Developer",
    "performance_score": 2.9,
    "client_satisfaction": 4.8,
    "internal_project_contribution": 2.0,
    "active_projects": 1.0,
    "project_complexity_score": 1.0,
    "delivery_quality_score": 81.0,
    "innovation_contribution": 5.8,
    "training_hours": 51.0,
    "mentorship_hours": -20.0,
    "promotion_readiness": 57.5,
    "flight_risk_score": 52.0,
    "engagement_score": 6.7,
    "knowledge_sharing_index": 3.8,
    "manager_id": 783300,
    "total_comp": 92400.00000000001,
    "team_lead_projects": 0.0,
    "direct_reports": 0.0
  },
  {
    "employee_id": 382554.0,
    "full_name": "Henry Santiago",
    "department": "Product Architecture",
    "position": "Integration Specialist",
    "level": "mid",
    "hire_date": "2019-07-23",
    "city": "Singapore",
    "country": "Singapore",
    "region": "APAC",
    "remote_work_ratio": 0.6,
    "travel_percentage": 34.0,
    "base_salary": 149000.0,
    "billing_rate": 2100.0,
    "utilization_target": 76.0,
    "actual_utilization": 78.4,
    "primary_specialization": "System Integration",
    "secondary_specialization": "API Design",
    "industry_expertise": "Consumer Tech, Social Impact",
    "certifications": "AWS Solutions Architect, TOGAF, Azure Architect",
    "performance_score": 3.8,
    "client_satisfaction": 4.4,
    "internal_project_contribution": 5.0,
    "active_projects": 3.0,
    "project_complexity_score": 4.0,
    "delivery_quality_score": 90.2,
    "innovation_contribution": 6.8,
    "training_hours": 39.0,
    "mentorship_hours": 7.0,
    "promotion_readiness": 60.1,
    "flight_risk_score": 46.0,
    "engagement_score": 7.8,
    "knowledge_sharing_index": 5.1,
    "manager_id": 604201,
    "total_comp": 171350.0,
    "team_lead_projects": 1.0,
    "direct_reports": 0.0
  },
  {
    "employee_id": 735911.0,
    "full_name": "Maria Lynch",
    "department": "Design & UX",
    "position": "Design System Specialist",
    "level": "entry",
    "hire_date": "2022-05-29",
    "city": "New York",
    "country": "USA",
    "region": "Americas",
    "remote_work_ratio": 0.46,
    "travel_percentage": 10.0,
    "base_salary": 75000.0,
    "billing_rate": 1100.0,
    "utilization_target": 75.0,
    "actual_utilization": 76.6,
    "primary_specialization": "Design Thinking",
    "secondary_specialization": "Design Systems",
    "industry_expertise": "Industrial Tech, Enterprise Software, Consumer Tech",
    "certifications": "Human Factors International",
    "performance_score": 3.4,
    "client_satisfaction": 4.4,
    "internal_project_contribution": 3.0,
    "active_projects": 2.0,
    "project_complexity_score": 3.0,
    "delivery_quality_score": 79.2,
    "innovation_contribution": 5.6,
    "training_hours": 56.0,
    "mentorship_hours": -10.0,
    "promotion_readiness": 64.8,
    "flight_risk_score": 25.0,
    "engagement_score": 8.1,
    "knowledge_sharing_index": 3.5,
    "manager_id": 238968,
    "total_comp": 82500.0,
    "team_lead_projects": 0.0,
    "direct_reports": 0.0
  },
  {
    "employee_id": 179451.0,
    "full_name": "Danielle Ford",
    "department": "Design & UX",
    "position": "UI Designer I",
    "level": "entry",
    "hire_date": "2023-08-04",
    "city": "San Francisco",
    "country": "USA",
    "region": "Americas",
    "remote_work_ratio": 0.4,
    "travel_percentage": 7.0,
    "base_salary": 83000.0,
    "billing_rate": 1400.0,
    "utilization_target": 73.0,
    "actual_utilization": 73.3,
    "primary_specialization": "Design Thinking",
    "secondary_specialization": "Service Design",
    "industry_expertise": "EdTech, Enterprise Software",
    "certifications": "Google UX Design, Human Factors International",
    "performance_score": 4.1,
    "client_satisfaction": 4.5,
    "internal_project_contribution": 1.0,
    "active_projects": 2.0,
    "project_complexity_score": 2.0,
    "delivery_quality_score": 96.0,
    "innovation_contribution": 5.8,
    "training_hours": 56.0,
    "mentorship_hours": -16.0,
    "promotion_readiness": 42.0,
    "flight_risk_score": 35.0,
    "engagement_score": 8.3,
    "knowledge_sharing_index": 2.2,
    "manager_id": 883794,
    "total_comp": 91300.00000000001,
    "team_lead_projects": 0.0,
    "direct_reports": 0.0
  },
  {
    "employee_id": 283060.0,
    "full_name": "Margaret Hawkins DDS",
    "department": "Product Strategy",
    "position": "Market Researcher",
    "level": "entry",
    "hire_date": "2022-07-07",
    "city": "San Francisco",
    "country": "USA",
    "region": "Americas",
    "remote_work_ratio": 0.5,
    "travel_percentage": 21.0,
    "base_salary": 97000.0,
    "billing_rate": 1600.0,
    "utilization_target": 75.0,
    "actual_utilization": 79.4,
    "primary_specialization": "Market Analysis",
    "secondary_specialization": "Product Discovery",
    "industry_expertise": "Industrial Tech, HealthTech, Consumer Tech, Enterprise Software",
    "certifications": "Agile Product Management, Product Management (PMP)",
    "performance_score": 2.9,
    "client_satisfaction": 4.7,
    "internal_project_contribution": 2.0,
    "active_projects": 3.0,
    "project_complexity_score": 3.0,
    "delivery_quality_score": 87.4,
    "innovation_contribution": 5.9,
    "training_hours": 54.0,
    "mentorship_hours": -28.0,
    "promotion_readiness": 68.5,
    "flight_risk_score": 35.0,
    "engagement_score": 7.0,
    "knowledge_sharing_index": 2.6,
    "manager_id": 72574,
    "total_comp": 106700.00000000001,
    "team_lead_projects": 0.0,
    "direct_reports": 0.0
  },
  {
    "employee_id": 883794.0,
    "full_name": "Amy Underwood",
    "department": "Design & UX",
    "position": "Design Director",
    "level": "senior",
    "hire_date": "2016-05-30",
    "city": "London",
    "country": "UK",
    "region": "EMEA",
    "remote_work_ratio": 0.68,
    "travel_percentage": 21.0,
    "base_salary": 196000.0,
    "billing_rate": 2500.0,
    "utilization_target": 59.0,
    "actual_utilization": 74.3,
    "primary_specialization": "Mobile Design",
    "secondary_specialization": "Web Applications",
    "industry_expertise": "EdTech, Industrial Tech, Social Impact",
    "certifications": "Human Factors International, Interaction Design Foundation",
    "performance_score": 4.3,
    "client_satisfaction": 4.4,
    "internal_project_contribution": 6.0,
    "active_projects": 4.0,
    "project_complexity_score": 5.0,
    "delivery_quality_score": 96.9,
    "innovation_contribution": 10.0,
    "training_hours": 33.0,
    "mentorship_hours": 37.0,
    "promotion_readiness": 22.42547006934152,
    "flight_risk_score": 54.0,
    "engagement_score": 8.1,
    "knowledge_sharing_index": 8.8,
    "manager_id": null,
    "total_comp": 235200.0,
    "team_lead_projects": 4.0,
    "direct_reports": 5.0
  },
  {
    "employee_id": 844151.0,
    "full_name": "Derek Clark",
    "department": "Engineering Delivery",
    "position": "Senior Developer",
    "level": "mid",
    "hire_date": "2019-04-13",
    "city": "New York",
    "country": "USA",
    "region": "Americas",
    "remote_work_ratio": 0.71,
    "travel_percentage": 13.0,
    "base_salary": 152000.0,
    "billing_rate": 1800.0,
    "utilization_target": 79.0,
    "actual_utilization": 74.3,
    "primary_specialization": "Frontend",
    "secondary_specialization": "Cloud Native",
    "industry_expertise": "FinTech, Enterprise Software, Social Impact, Consumer Tech",
    "certifications": "AWS Developer, Azure Developer",
    "performance_score": 4.0,
    "client_satisfaction": 4.3,
    "internal_project_contribution": 4.0,
    "active_projects": 1.0,
    "project_complexity_score": 3.0,
    "delivery_quality_score": 92.1,
    "innovation_contribution": 6.5,
    "training_hours": 40.0,
    "mentorship_hours": -4.0,
    "promotion_readiness": 73.2,
    "flight_risk_score": 41.0,
    "engagement_score": 8.0,
    "knowledge_sharing_index": 5.1,
    "manager_id": 783300,
    "total_comp": 174800.0,
    "team_lead_projects": 0.0,
    "direct_reports": 0.0
  },
  {
    "employee_id": 988712.0,
    "full_name": "Michelle Lewis",
    "department": "Product Strategy",
    "position": "Strategy Director",
    "level": "senior",
    "hire_date": "2018-02-01",
    "city": "Singapore",
    "country": "Singapore",
    "region": "APAC",
    "remote_work_ratio": 0.59,
    "travel_percentage": 50.0,
    "base_salary": 173000.0,
    "billing_rate": 3500.0,
    "utilization_target": 59.0,
    "actual_utilization": 66.4,
    "primary_specialization": "Digital Transformation",
    "secondary_specialization": "Digital Transformation",
    "industry_expertise": "Enterprise Software, EdTech",
    "certifications": "PSPO, Product Management (PMP)",
    "performance_score": 4.2,
    "client_satisfaction": 4.2,
    "internal_project_contribution": 7.0,
    "active_projects": 5.0,
    "project_complexity_score": 4.0,
    "delivery_quality_score": 94.4,
    "innovation_contribution": 9.7,
    "training_hours": 26.0,
    "mentorship_hours": 34.0,
    "promotion_readiness": 20.983949137384524,
    "flight_risk_score": 69.0,
    "engagement_score": 7.2,
    "knowledge_sharing_index": 8.2,
    "manager_id": null,
    "total_comp": 207600.0,
    "team_lead_projects": 3.0,
    "direct_reports": 3.0
  },
  {
    "employee_id": 523481.0,
    "full_name": "Thomas Ellis",
    "department": "Product Architecture",
    "position": "Solution Architect",
    "level": "mid",
    "hire_date": "2020-04-04",
    "city": "London",
    "country": "UK",
    "region": "EMEA",
    "remote_work_ratio": 0.62,
    "travel_percentage": 25.0,
    "base_salary": 132000.0,
    "billing_rate": 2100.0,
    "utilization_target": 77.0,
    "actual_utilization": 72.9,
    "primary_specialization": "Security Architecture",
    "secondary_specialization": "Microservices",
    "industry_expertise": "Enterprise Software, FinTech",
    "certifications": "AWS Solutions Architect, TOGAF, Google Cloud Architect",
    "performance_score": 4.0,
    "client_satisfaction": 4.3,
    "internal_project_contribution": 4.0,
    "active_projects": 3.0,
    "project_complexity_score": 3.0,
    "delivery_quality_score": 93.9,
    "innovation_contribution": 7.0,
    "training_hours": 40.0,
    "mentorship_hours": -10.0,
    "promotion_readiness": 89.0,
    "flight_risk_score": 51.0,
    "engagement_score": 6.7,
    "knowledge_sharing_index": 6.9,
    "manager_id": 604201,
    "total_comp": 151800.0,
    "team_lead_projects": 0.0,
    "direct_reports": 0.0
  },
  {
    "employee_id": 277746.0,
    "full_name": "Patrick Ryan",
    "department": "Product Strategy",
    "position": "Domain Expert",
    "level": "mid",
    "hire_date": "2021-02-22",
    "city": "San Francisco",
    "country": "USA",
    "region": "Americas",
    "remote_work_ratio": 0.49,
    "travel_percentage": 42.0,
    "base_salary": 153000.0,
    "billing_rate": 1900.0,
    "utilization_target": 71.0,
    "actual_utilization": 75.8,
    "primary_specialization": "Product Discovery",
    "secondary_specialization": "Product Discovery",
    "industry_expertise": "Social Impact, E-commerce, HealthTech",
    "certifications": "Agile Product Management, PSPO",
    "performance_score": 3.6,
    "client_satisfaction": 4.2,
    "internal_project_contribution": 4.0,
    "active_projects": 4.0,
    "project_complexity_score": 4.0,
    "delivery_quality_score": 89.7,
    "innovation_contribution": 7.1,
    "training_hours": 40.0,
    "mentorship_hours": -5.0,
    "promotion_readiness": 74.5,
    "flight_risk_score": 42.0,
    "engagement_score": 8.1,
    "knowledge_sharing_index": 5.0,
    "manager_id": 442666,
    "total_comp": 175950.0,
    "team_lead_projects": 1.0,
    "direct_reports": 0.0
  },
  {
    "employee_id": 783300.0,
    "full_name": "Stephanie Ross",
    "department": "Engineering Delivery",
    "position": "CTO",
    "level": "senior",
    "hire_date": "2018-11-22",
    "city": "San Francisco",
    "country": "USA",
    "region": "Americas",
    "remote_work_ratio": 0.9,
    "travel_percentage": 15.0,
    "base_salary": 195000.0,
    "billing_rate": 2600.0,
    "utilization_target": 70.0,
    "actual_utilization": 69.8,
    "primary_specialization": "DevOps",
    "secondary_specialization": "Mobile Development",
    "industry_expertise": "Industrial Tech, Enterprise Software, FinTech, Consumer Tech",
    "certifications": "Kubernetes, Scrum Master, AWS Developer",
    "performance_score": 4.0,
    "client_satisfaction": 4.2,
    "internal_project_contribution": 6.0,
    "active_projects": 3.0,
    "project_complexity_score": 5.0,
    "delivery_quality_score": 90.4,
    "innovation_contribution": 8.3,
    "training_hours": 37.0,
    "mentorship_hours": 30.0,
    "promotion_readiness": 10.55431582842505,
    "flight_risk_score": 49.0,
    "engagement_score": 7.0,
    "knowledge_sharing_index": 7.5,
    "manager_id": null,
    "total_comp": 234000.0,
    "team_lead_projects": 3.0,
    "direct_reports": 5.0
  },
  {
    "employee_id": 229974.0,
    "full_name": "Brenda Snyder PhD",
    "department": "Design & UX",
    "position": "UX Researcher I",
    "level": "entry",
    "hire_date": "2023-09-01",
    "city": "London",
    "country": "UK",
    "region": "EMEA",
    "remote_work_ratio": 0.55,
    "travel_percentage": 15.0,
    "base_salary": 88000.0,
    "billing_rate": 1100.0,
    "utilization_target": 76.0,
    "actual_utilization": 70.5,
    "primary_specialization": "Service Design",
    "secondary_specialization": "Service Design",
    "industry_expertise": "Social Impact, FinTech, HealthTech, E-commerce",
    "certifications": "Interaction Design Foundation",
    "performance_score": 3.1,
    "client_satisfaction": 4.1,
    "internal_project_contribution": 1.0,
    "active_projects": 2.0,
    "project_complexity_score": 2.0,
    "delivery_quality_score": 88.6,
    "innovation_contribution": 5.5,
    "training_hours": 41.0,
    "mentorship_hours": -13.0,
    "promotion_readiness": 51.7,
    "flight_risk_score": 28.0,
    "engagement_score": 7.8,
    "knowledge_sharing_index": 3.5,
    "manager_id": 883794,
    "total_comp": 96800.00000000001,
    "team_lead_projects": 0.0,
    "direct_reports": 0.0
  },
  {
    "employee_id": 902931.0,
    "full_name": "Mark Conner",
    "department": "Product Architecture",
    "position": "Technical Director",
    "level": "senior",
    "hire_date": "2015-10-26",
    "city": "Berlin",
    "country": "Germany",
    "region": "EMEA",
    "remote_work_ratio": 0.79,
    "travel_percentage": 35.0,
    "base_salary": 214000.0,
    "billing_rate": 2400.0,
    "utilization_target": 67.0,
    "actual_utilization": 74.6,
    "primary_specialization": "Cloud Infrastructure",
    "secondary_specialization": "API Design",
    "industry_expertise": "HealthTech, Social Impact, Consumer Tech",
    "certifications": "AWS Solutions Architect, Google Cloud Architect, TOGAF, Azure Architect",
    "performance_score": 4.0,
    "client_satisfaction": 4.1,
    "internal_project_contribution": 5.0,
    "active_projects": 2.0,
    "project_complexity_score": 5.0,
    "delivery_quality_score": 89.3,
    "innovation_contribution": 8.6,
    "training_hours": 39.0,
    "mentorship_hours": 27.0,
    "promotion_readiness": 23.27080619094652,
    "flight_risk_score": 44.0,
    "engagement_score": 7.4,
    "knowledge_sharing_index": 7.9,
    "manager_id": null,
    "total_comp": 256800.0,
    "team_lead_projects": 1.0,
    "direct_reports": 2.0
  },
  {
    "employee_id": 442666.0,
    "full_name": "Janice Carlson",
    "department": "Product Strategy",
    "position": "Strategy Director",
    "level": "senior",
    "hire_date": "2012-08-17",
    "city": "San Francisco",
    "country": "USA",
    "region": "Americas",
    "remote_work_ratio": 0.62,
    "travel_percentage": 49.0,
    "base_salary": 268000.0,
    "billing_rate": 3400.0,
    "utilization_target": 59.0,
    "actual_utilization": 69.2,
    "primary_specialization": "Digital Transformation",
    "secondary_specialization": "Innovation Strategy",
    "industry_expertise": "E-commerce, Social Impact",
    "certifications": "Product Management (PMP), PSPO",
    "performance_score": 4.1,
    "client_satisfaction": 4.3,
    "internal_project_contribution": 7.0,
    "active_projects": 4.0,
    "project_complexity_score": 4.0,
    "delivery_quality_score": 94.7,
    "innovation_contribution": 9.1,
    "training_hours": 29.0,
    "mentorship_hours": 34.0,
    "promotion_readiness": 2.135392804604378,
    "flight_risk_score": 34.0,
    "engagement_score": 8.3,
    "knowledge_sharing_index": 8.6,
    "manager_id": null,
    "total_comp": 321600.0,
    "team_lead_projects": 4.0,
    "direct_reports": 2.0
  },
  {
    "employee_id": 490785.0,
    "full_name": "Tricia Valencia",
    "department": "Design & UX",
    "position": "Design Lead",
    "level": "mid",
    "hire_date": "2021-05-11",
    "city": "San Francisco",
    "country": "USA",
    "region": "Americas",
    "remote_work_ratio": 0.61,
    "travel_percentage": 21.0,
    "base_salary": 149000.0,
    "billing_rate": 2000.0,
    "utilization_target": 68.0,
    "actual_utilization": 68.3,
    "primary_specialization": "Design Systems",
    "secondary_specialization": "Service Design",
    "industry_expertise": "Social Impact, Enterprise Software, FinTech, EdTech",
    "certifications": "Human Factors International, Interaction Design Foundation, Google UX Design",
    "performance_score": 3.5,
    "client_satisfaction": 4.4,
    "internal_project_contribution": 4.0,
    "active_projects": 3.0,
    "project_complexity_score": 3.0,
    "delivery_quality_score": 92.1,
    "innovation_contribution": 8.2,
    "training_hours": 43.0,
    "mentorship_hours": 13.0,
    "promotion_readiness": 67.9,
    "flight_risk_score": 36.0,
    "engagement_score": 6.6,
    "knowledge_sharing_index": 4.7,
    "manager_id": 238968,
    "total_comp": 171350.0,
    "team_lead_projects": 2.0,
    "direct_reports": 0.0
  },
  {
    "employee_id": 12038.0,
    "full_name": "Ashley Dyer",
    "department": "Client Services",
    "position": "Partnership Director",
    "level": "senior",
    "hire_date": "2018-10-10",
    "city": "San Francisco",
    "country": "USA",
    "region": "Americas",
    "remote_work_ratio": 0.6,
    "travel_percentage": 62.0,
    "base_salary": 172000.0,
    "billing_rate": 2100.0,
    "utilization_target": 76.0,
    "actual_utilization": 74.4,
    "primary_specialization": "Portfolio Management",
    "secondary_specialization": "Change Management",
    "industry_expertise": "EdTech, Consumer Tech",
    "certifications": "Prince2, PMP, Agile Project Management",
    "performance_score": 4.0,
    "client_satisfaction": 4.3,
    "internal_project_contribution": 6.0,
    "active_projects": 5.0,
    "project_complexity_score": 4.0,
    "delivery_quality_score": 92.3,
    "innovation_contribution": 6.9,
    "training_hours": 35.0,
    "mentorship_hours": 29.0,
    "promotion_readiness": 19.877506109742864,
    "flight_risk_score": 45.0,
    "engagement_score": 8.1,
    "knowledge_sharing_index": 8.1,
    "manager_id": null,
    "total_comp": 206400.0,
    "team_lead_projects": 5.0,
    "direct_reports": 0.0
  },
  {
    "employee_id": 787352.0,
    "full_name": "Martin Rodriguez",
    "department": "Engineering Delivery",
    "position": "Senior Developer",
    "level": "mid",
    "hire_date": "2020-03-10",
    "city": "London",
    "country": "UK",
    "region": "EMEA",
    "remote_work_ratio": 0.72,
    "travel_percentage": 18.0,
    "base_salary": 159000.0,
    "billing_rate": 2100.0,
    "utilization_target": 78.0,
    "actual_utilization": 82.4,
    "primary_specialization": "DevOps",
    "secondary_specialization": "DevOps",
    "industry_expertise": "Enterprise Software, Social Impact",
    "certifications": "Scrum Master, Azure Developer, Kubernetes",
    "performance_score": 3.2,
    "client_satisfaction": 4.6,
    "internal_project_contribution": 3.0,
    "active_projects": 2.0,
    "project_complexity_score": 3.0,
    "delivery_quality_score": 88.1,
    "innovation_contribution": 7.9,
    "training_hours": 44.0,
    "mentorship_hours": 18.0,
    "promotion_readiness": 82.9,
    "flight_risk_score": 27.0,
    "engagement_score": 6.6,
    "knowledge_sharing_index": 5.9,
    "manager_id": 199659,
    "total_comp": 182850.0,
    "team_lead_projects": 0.0,
    "direct_reports": 0.0
  },
  {
    "employee_id": 455884.0,
    "full_name": "Aaron Bowen",
    "department": "Design & UX",
    "position": "UX Researcher I",
    "level": "entry",
    "hire_date": "2022-06-16",
    "city": "New York",
    "country": "USA",
    "region": "Americas",
    "remote_work_ratio": 0.4,
    "travel_percentage": 9.0,
    "base_salary": 80000.0,
    "billing_rate": 1400.0,
    "utilization_target": 73.0,
    "actual_utilization": 83.9,
    "primary_specialization": "Design Thinking",
    "secondary_specialization": "Web Applications",
    "industry_expertise": "Social Impact, Industrial Tech, Consumer Tech",
    "certifications": "Interaction Design Foundation, Human Factors International",
    "performance_score": 3.2,
    "client_satisfaction": 4.8,
    "internal_project_contribution": 1.0,
    "active_projects": 3.0,
    "project_complexity_score": 3.0,
    "delivery_quality_score": 86.1,
    "innovation_contribution": 5.7,
    "training_hours": 46.0,
    "mentorship_hours": -11.0,
    "promotion_readiness": 60.3,
    "flight_risk_score": 28.0,
    "engagement_score": 8.2,
    "knowledge_sharing_index": 2.6,
    "manager_id": 238968,
    "total_comp": 88000.0,
    "team_lead_projects": 0.0,
    "direct_reports": 0.0
  },
  {
    "employee_id": 754639.0,
    "full_name": "Jonathan White",
    "department": "Product Strategy",
    "position": "Senior Product Manager",
    "level": "mid",
    "hire_date": "2019-02-27",
    "city": "San Francisco",
    "country": "USA",
    "region": "Americas",
    "remote_work_ratio": 0.45,
    "travel_percentage": 35.0,
    "base_salary": 148000.0,
    "billing_rate": 2400.0,
    "utilization_target": 70.0,
    "actual_utilization": 78.2,
    "primary_specialization": "Innovation Strategy",
    "secondary_specialization": "Product Discovery",
    "industry_expertise": "Industrial Tech, E-commerce, EdTech, Social Impact",
    "certifications": "Agile Product Management, PSPO, Product Management (PMP)",
    "performance_score": 3.9,
    "client_satisfaction": 4.8,
    "internal_project_contribution": 3.0,
    "active_projects": 4.0,
    "project_complexity_score": 3.0,
    "delivery_quality_score": 86.8,
    "innovation_contribution": 8.7,
    "training_hours": 43.0,
    "mentorship_hours": -9.0,
    "promotion_readiness": 67.7,
    "flight_risk_score": 50.0,
    "engagement_score": 7.9,
    "knowledge_sharing_index": 6.4,
    "manager_id": 988712,
    "total_comp": 170200.0,
    "team_lead_projects": 2.0,
    "direct_reports": 0.0
  },
  {
    "employee_id": 956959.0,
    "full_name": "Mario Skinner",
    "department": "Design & UX",
    "position": "UX Researcher I",
    "level": "entry",
    "hire_date": "2023-11-25",
    "city": "Berlin",
    "country": "Germany",
    "region": "EMEA",
    "remote_work_ratio": 0.43,
    "travel_percentage": 15.0,
    "base_salary": 79000.0,
    "billing_rate": 1000.0,
    "utilization_target": 76.0,
    "actual_utilization": 67.0,
    "primary_specialization": "User Research",
    "secondary_specialization": "Mobile Design",
    "industry_expertise": "E-commerce, Enterprise Software, Consumer Tech, HealthTech",
    "certifications": "Interaction Design Foundation",
    "performance_score": 3.7,
    "client_satisfaction": 4.6,
    "internal_project_contribution": 2.0,
    "active_projects": 3.0,
    "project_complexity_score": 3.0,
    "delivery_quality_score": 83.3,
    "innovation_contribution": 6.8,
    "training_hours": 60.0,
    "mentorship_hours": -28.0,
    "promotion_readiness": 74.1,
    "flight_risk_score": 63.0,
    "engagement_score": 8.2,
    "knowledge_sharing_index": 2.8,
    "manager_id": 238968,
    "total_comp": 86900.0,
    "team_lead_projects": 0.0,
    "direct_reports": 0.0
  },
  {
    "employee_id": 532323.0,
    "full_name": "Brittany Farmer",
    "department": "Product Strategy",
    "position": "Domain Expert",
    "level": "mid",
    "hire_date": "2021-10-20",
    "city": "San Francisco",
    "country": "USA",
    "region": "Americas",
    "remote_work_ratio": 0.52,
    "travel_percentage": 37.0,
    "base_salary": 136000.0,
    "billing_rate": 1900.0,
    "utilization_target": 69.0,
    "actual_utilization": 66.8,
    "primary_specialization": "Digital Transformation",
    "secondary_specialization": "Digital Transformation",
    "industry_expertise": "E-commerce, Consumer Tech, Industrial Tech",
    "certifications": "Product Management (PMP), Agile Product Management",
    "performance_score": 4.1,
    "client_satisfaction": 4.6,
    "internal_project_contribution": 4.0,
    "active_projects": 4.0,
    "project_complexity_score": 4.0,
    "delivery_quality_score": 83.9,
    "innovation_contribution": 7.9,
    "training_hours": 37.0,
    "mentorship_hours": 6.0,
    "promotion_readiness": 71.5,
    "flight_risk_score": 63.0,
    "engagement_score": 8.1,
    "knowledge_sharing_index": 4.5,
    "manager_id": 72574,
    "total_comp": 156400.0,
    "team_lead_projects": 0.0,
    "direct_reports": 0.0
  },
  {
    "employee_id": 565579.0,
    "full_name": "Tammy Sellers",
    "department": "Product Strategy",
    "position": "Domain Expert",
    "level": "mid",
    "hire_date": "2018-03-04",
    "city": "Singapore",
    "country": "Singapore",
    "region": "APAC",
    "remote_work_ratio": 0.45,
    "travel_percentage": 44.0,
    "base_salary": 118000.0,
    "billing_rate": 2100.0,
    "utilization_target": 69.0,
    "actual_utilization": 70.1,
    "primary_specialization": "Digital Transformation",
    "secondary_specialization": "Product Discovery",
    "industry_expertise": "E-commerce, FinTech, Enterprise Software",
    "certifications": "PSPO, Agile Product Management, Product Management (PMP)",
    "performance_score": 4.0,
    "client_satisfaction": 4.6,
    "internal_project_contribution": 4.0,
    "active_projects": 4.0,
    "project_complexity_score": 3.0,
    "delivery_quality_score": 77.0,
    "innovation_contribution": 9.0,
    "training_hours": 45.0,
    "mentorship_hours": -7.0,
    "promotion_readiness": 64.5,
    "flight_risk_score": 56.0,
    "engagement_score": 7.2,
    "knowledge_sharing_index": 4.9,
    "manager_id": 988712,
    "total_comp": 135700.0,
    "team_lead_projects": 3.0,
    "direct_reports": 0.0
  },
  {
    "employee_id": 628038.0,
    "full_name": "Alec Hickman",
    "department": "Product Architecture",
    "position": "Technical Documentation Specialist",
    "level": "entry",
    "hire_date": "2022-11-22",
    "city": "New York",
    "country": "USA",
    "region": "Americas",
    "remote_work_ratio": 0.55,
    "travel_percentage": 16.0,
    "base_salary": 98000.0,
    "billing_rate": 1400.0,
    "utilization_target": 78.0,
    "actual_utilization": 77.1,
    "primary_specialization": "API Design",
    "secondary_specialization": "System Integration",
    "industry_expertise": "Consumer Tech, HealthTech",
    "certifications": "TOGAF",
    "performance_score": 4.2,
    "client_satisfaction": 4.5,
    "internal_project_contribution": 3.0,
    "active_projects": 1.0,
    "project_complexity_score": 3.0,
    "delivery_quality_score": 85.7,
    "innovation_contribution": 4.8,
    "training_hours": 60.0,
    "mentorship_hours": -10.0,
    "promotion_readiness": 41.6,
    "flight_risk_score": 70.0,
    "engagement_score": 7.4,
    "knowledge_sharing_index": 3.2,
    "manager_id": 604201,
    "total_comp": 107800.00000000001,
    "team_lead_projects": 0.0,
    "direct_reports": 0.0
  },
  {
    "employee_id": 921406.0,
    "full_name": "Dr. Cynthia Allen",
    "department": "Product Architecture",
    "position": "Enterprise Architect",
    "level": "mid",
    "hire_date": "2020-03-03",
    "city": "Berlin",
    "country": "Germany",
    "region": "EMEA",
    "remote_work_ratio": 0.75,
    "travel_percentage": 27.0,
    "base_salary": 122000.0,
    "billing_rate": 2000.0,
    "utilization_target": 77.0,
    "actual_utilization": 75.6,
    "primary_specialization": "System Integration",
    "secondary_specialization": "Microservices",
    "industry_expertise": "Industrial Tech, EdTech, E-commerce",
    "certifications": "AWS Solutions Architect, Azure Architect, Google Cloud Architect",
    "performance_score": 3.9,
    "client_satisfaction": 4.1,
    "internal_project_contribution": 3.0,
    "active_projects": 3.0,
    "project_complexity_score": 4.0,
    "delivery_quality_score": 90.3,
    "innovation_contribution": 6.2,
    "training_hours": 42.0,
    "mentorship_hours": -10.0,
    "promotion_readiness": 65.6,
    "flight_risk_score": 27.0,
    "engagement_score": 7.4,
    "knowledge_sharing_index": 6.0,
    "manager_id": 604201,
    "total_comp": 140300.0,
    "team_lead_projects": 1.0,
    "direct_reports": 0.0
  },
  {
    "employee_id": 594916.0,
    "full_name": "Angelica Tucker",
    "department": "Client Services",
    "position": "Head of Client Services",
    "level": "senior",
    "hire_date": "2014-11-03",
    "city": "San Francisco",
    "country": "USA",
    "region": "Americas",
    "remote_work_ratio": 0.42,
    "travel_percentage": 57.0,
    "base_salary": 168000.0,
    "billing_rate": 2800.0,
    "utilization_target": 75.0,
    "actual_utilization": 83.3,
    "primary_specialization": "Digital Strategy",
    "secondary_specialization": "Agile Delivery",
    "industry_expertise": "Industrial Tech, Consumer Tech, E-commerce, Enterprise Software",
    "certifications": "PMP, Prince2",
    "performance_score": 4.5,
    "client_satisfaction": 4.8,
    "internal_project_contribution": 6.0,
    "active_projects": 8.0,
    "project_complexity_score": 4.0,
    "delivery_quality_score": 94.8,
    "innovation_contribution": 6.4,
    "training_hours": 37.0,
    "mentorship_hours": 24.0,
    "promotion_readiness": 11.659374934504275,
    "flight_risk_score": 43.0,
    "engagement_score": 7.8,
    "knowledge_sharing_index": 8.5,
    "manager_id": null,
    "total_comp": 210000.0,
    "team_lead_projects": 5.0,
    "direct_reports": 0.0
  },
  {
    "employee_id": 72574.0,
    "full_name": "Kim Martinez",
    "department": "Product Strategy",
    "position": "Innovation Lead",
    "level": "senior",
    "hire_date": "2017-04-10",
    "city": "Berlin",
    "country": "Germany",
    "region": "EMEA",
    "remote_work_ratio": 0.68,
    "travel_percentage": 50.0,
    "base_salary": 249000.0,
    "billing_rate": 3100.0,
    "utilization_target": 62.0,
    "actual_utilization": 70.6,
    "primary_specialization": "Go-to-Market",
    "secondary_specialization": "Innovation Strategy",
    "industry_expertise": "Industrial Tech, HealthTech, E-commerce",
    "certifications": "PSPO, Agile Product Management",
    "performance_score": 4.1,
    "client_satisfaction": 4.4,
    "internal_project_contribution": 6.0,
    "active_projects": 3.0,
    "project_complexity_score": 5.0,
    "delivery_quality_score": 95.5,
    "innovation_contribution": 9.2,
    "training_hours": 23.0,
    "mentorship_hours": 34.0,
    "promotion_readiness": 2.750202714525626,
    "flight_risk_score": 33.0,
    "engagement_score": 7.8,
    "knowledge_sharing_index": 8.2,
    "manager_id": null,
    "total_comp": 298800.0,
    "team_lead_projects": 3.0,
    "direct_reports": 2.0
  },
  {
    "employee_id": 691798.0,
    "full_name": "Joshua Baker",
    "department": "Engineering Delivery",
    "position": "Associate Developer",
    "level": "entry",
    "hire_date": "2021-08-26",
    "city": "San Francisco",
    "country": "USA",
    "region": "Americas",
    "remote_work_ratio": 0.76,
    "travel_percentage": 5.0,
    "base_salary": 137000.0,
    "billing_rate": 1800.0,
    "utilization_target": 84.0,
    "actual_utilization": 45.0,
    "primary_specialization": "Cloud Native",
    "secondary_specialization": "Full Stack",
    "industry_expertise": "E-commerce, HealthTech, Social Impact",
    "certifications": "Kubernetes, AWS Developer",
    "performance_score": 2.0,
    "client_satisfaction": 3.0,
    "internal_project_contribution": 1.0,
    "active_projects": 1.0,
    "project_complexity_score": 4.0,
    "delivery_quality_score": 98.0,
    "innovation_contribution": 4.6,
    "training_hours": 100.0,
    "mentorship_hours": -29.0,
    "promotion_readiness": 89.2,
    "flight_risk_score": 85.0,
    "engagement_score": 3.0,
    "knowledge_sharing_index": 10.0,
    "manager_id": 783300,
    "total_comp": 150700.0,
    "team_lead_projects": 0.0,
    "direct_reports": 0.0
  },
  {
    "employee_id": 914812.0,
    "full_name": "Tracey Hickman",
    "department": "Engineering Delivery",
    "position": "Cloud Architect",
    "level": "mid",
    "hire_date": "2018-09-04",
    "city": "Singapore",
    "country": "Singapore",
    "region": "APAC",
    "remote_work_ratio": 0.72,
    "travel_percentage": 15.0,
    "base_salary": 170000.0,
    "billing_rate": 1500.0,
    "utilization_target": 81.0,
    "actual_utilization": 82.3,
    "primary_specialization": "Cloud Native",
    "secondary_specialization": "Backend",
    "industry_expertise": "FinTech, Industrial Tech, Enterprise Software",
    "certifications": "Scrum Master, Azure Developer, AWS Developer",
    "performance_score": 3.8,
    "client_satisfaction": 4.4,
    "internal_project_contribution": 4.0,
    "active_projects": 1.0,
    "project_complexity_score": 3.0,
    "delivery_quality_score": 92.2,
    "innovation_contribution": 6.6,
    "training_hours": 34.0,
    "mentorship_hours": -8.0,
    "promotion_readiness": 60.0,
    "flight_risk_score": 59.0,
    "engagement_score": 7.8,
    "knowledge_sharing_index": 5.6,
    "manager_id": 783300,
    "total_comp": 195499.99999999997,
    "team_lead_projects": 0.0,
    "direct_reports": 0.0
  },
  {
    "employee_id": 791952.0,
    "full_name": "Christina Collins",
    "department": "Client Services",
    "position": "Partnership Director",
    "level": "senior",
    "hire_date": "2015-09-13",
    "city": "New York",
    "country": "USA",
    "region": "Americas",
    "remote_work_ratio": 0.49,
    "travel_percentage": 61.0,
    "base_salary": 171000.0,
    "billing_rate": 2600.0,
    "utilization_target": 76.0,
    "actual_utilization": 78.0,
    "primary_specialization": "Strategic Planning",
    "secondary_specialization": "Digital Strategy",
    "industry_expertise": "Industrial Tech, HealthTech, Enterprise Software",
    "certifications": "Scrum Master, PMP, Agile Project Management",
    "performance_score": 4.4,
    "client_satisfaction": 4.6,
    "internal_project_contribution": 6.0,
    "active_projects": 8.0,
    "project_complexity_score": 5.0,
    "delivery_quality_score": 92.1,
    "innovation_contribution": 7.5,
    "training_hours": 31.0,
    "mentorship_hours": 24.0,
    "promotion_readiness": 20.6046310640093,
    "flight_risk_score": 50.0,
    "engagement_score": 6.6,
    "knowledge_sharing_index": 8.7,
    "manager_id": null,
    "total_comp": 205200.0,
    "team_lead_projects": 8.0,
    "direct_reports": 1.0
  },
  {
    "employee_id": 704314.0,
    "full_name": "Jessica Holmes",
    "department": "Product Architecture",
    "position": "Integration Specialist",
    "level": "mid",
    "hire_date": "2019-11-30",
    "city": "London",
    "country": "UK",
    "region": "EMEA",
    "remote_work_ratio": 0.76,
    "travel_percentage": 31.0,
    "base_salary": 150000.0,
    "billing_rate": 2000.0,
    "utilization_target": 74.0,
    "actual_utilization": 67.4,
    "primary_specialization": "System Integration",
    "secondary_specialization": "Security Architecture",
    "industry_expertise": "FinTech, E-commerce, Social Impact",
    "certifications": "TOGAF, AWS Solutions Architect, Google Cloud Architect",
    "performance_score": 3.8,
    "client_satisfaction": 4.1,
    "internal_project_contribution": 4.0,
    "active_projects": 2.0,
    "project_complexity_score": 3.0,
    "delivery_quality_score": 86.7,
    "innovation_contribution": 6.7,
    "training_hours": 47.0,
    "mentorship_hours": 1.0,
    "promotion_readiness": 59.6,
    "flight_risk_score": 37.0,
    "engagement_score": 7.6,
    "knowledge_sharing_index": 6.4,
    "manager_id": 732052,
    "total_comp": 172500.0,
    "team_lead_projects": 0.0,
    "direct_reports": 0.0
  },
  {
    "employee_id": 126882.0,
    "full_name": "Austin Smith",
    "department": "Client Services",
    "position": "Program Manager",
    "level": "mid",
    "hire_date": "2018-03-21",
    "city": "New York",
    "country": "USA",
    "region": "Americas",
    "remote_work_ratio": 0.43,
    "travel_percentage": 45.0,
    "base_salary": 149000.0,
    "billing_rate": 2000.0,
    "utilization_target": 84.0,
    "actual_utilization": 68.6,
    "primary_specialization": "Change Management",
    "secondary_specialization": "Change Management",
    "industry_expertise": "FinTech, HealthTech, EdTech",
    "certifications": "Prince2, Scrum Master, Agile Project Management",
    "performance_score": 4.0,
    "client_satisfaction": 4.1,
    "internal_project_contribution": 5.0,
    "active_projects": 4.0,
    "project_complexity_score": 4.0,
    "delivery_quality_score": 90.0,
    "innovation_contribution": 5.8,
    "training_hours": 40.0,
    "mentorship_hours": -5.0,
    "promotion_readiness": 69.8,
    "flight_risk_score": 66.0,
    "engagement_score": 7.1,
    "knowledge_sharing_index": 6.8,
    "manager_id": 791952,
    "total_comp": 171350.0,
    "team_lead_projects": 2.0,
    "direct_reports": 0.0
  },
  {
    "employee_id": 580828.0,
    "full_name": "Daniel Jones",
    "department": "Product Architecture",
    "position": "Junior Solution Architect",
    "level": "entry",
    "hire_date": "2023-07-24",
    "city": "San Francisco",
    "country": "USA",
    "region": "Americas",
    "remote_work_ratio": 0.65,
    "travel_percentage": 10.0,
    "base_salary": 81000.0,
    "billing_rate": 1300.0,
    "utilization_target": 80.0,
    "actual_utilization": 77.1,
    "primary_specialization": "API Design",
    "secondary_specialization": "System Integration",
    "industry_expertise": "HealthTech, E-commerce",
    "certifications": "AWS Solutions Architect, Azure Architect",
    "performance_score": 3.9,
    "client_satisfaction": 4.5,
    "internal_project_contribution": 3.0,
    "active_projects": 2.0,
    "project_complexity_score": 3.0,
    "delivery_quality_score": 83.4,
    "innovation_contribution": 5.9,
    "training_hours": 41.0,
    "mentorship_hours": -23.0,
    "promotion_readiness": 55.8,
    "flight_risk_score": 58.0,
    "engagement_score": 6.6,
    "knowledge_sharing_index": 2.4,
    "manager_id": 902931,
    "total_comp": 89100.0,
    "team_lead_projects": 0.0,
    "direct_reports": 0.0
  },
  {
    "employee_id": 661759.0,
    "full_name": "Austin Johnson",
    "department": "Design & UX",
    "position": "Design Lead",
    "level": "mid",
    "hire_date": "2020-05-19",
    "city": "London",
    "country": "UK",
    "region": "EMEA",
    "remote_work_ratio": 0.57,
    "travel_percentage": 15.0,
    "base_salary": 145000.0,
    "billing_rate": 1600.0,
    "utilization_target": 70.0,
    "actual_utilization": 79.1,
    "primary_specialization": "Service Design",
    "secondary_specialization": "Service Design",
    "industry_expertise": "Consumer Tech, FinTech, Enterprise Software, EdTech",
    "certifications": "Google UX Design, Interaction Design Foundation, Human Factors International",
    "performance_score": 3.6,
    "client_satisfaction": 4.7,
    "internal_project_contribution": 5.0,
    "active_projects": 3.0,
    "project_complexity_score": 4.0,
    "delivery_quality_score": 84.2,
    "innovation_contribution": 8.4,
    "training_hours": 43.0,
    "mentorship_hours": -1.0,
    "promotion_readiness": 59.6,
    "flight_risk_score": 21.0,
    "engagement_score": 8.4,
    "knowledge_sharing_index": 4.5,
    "manager_id": 883794,
    "total_comp": 166750.0,
    "team_lead_projects": 0.0,
    "direct_reports": 0.0
  },
  {
    "employee_id": 346479.0,
    "full_name": "David Caldwell",
    "department": "Product Strategy",
    "position": "Innovation Lead",
    "level": "senior",
    "hire_date": "2014-12-12",
    "city": "Berlin",
    "country": "Germany",
    "region": "EMEA",
    "remote_work_ratio": 0.52,
    "travel_percentage": 51.0,
    "base_salary": 206000.0,
    "billing_rate": 3100.0,
    "utilization_target": 60.0,
    "actual_utilization": 72.9,
    "primary_specialization": "Go-to-Market",
    "secondary_specialization": "Go-to-Market",
    "industry_expertise": "Consumer Tech, EdTech",
    "certifications": "Product Management (PMP), PSPO",
    "performance_score": 4.2,
    "client_satisfaction": 4.4,
    "internal_project_contribution": 5.0,
    "active_projects": 4.0,
    "project_complexity_score": 5.0,
    "delivery_quality_score": 92.5,
    "innovation_contribution": 10.0,
    "training_hours": 40.0,
    "mentorship_hours": 24.0,
    "promotion_readiness": 7.088065468401728,
    "flight_risk_score": 29.0,
    "engagement_score": 7.0,
    "knowledge_sharing_index": 7.3,
    "manager_id": null,
    "total_comp": 247200.0,
    "team_lead_projects": 2.0,
    "direct_reports": 0.0
  },
  {
    "employee_id": 224643.0,
    "full_name": "Miranda Khan",
    "department": "Product Architecture",
    "position": "Junior Solution Architect",
    "level": "entry",
    "hire_date": "2022-03-29",
    "city": "New York",
    "country": "USA",
    "region": "Americas",
    "remote_work_ratio": 0.6,
    "travel_percentage": 18.0,
    "base_salary": 101000.0,
    "billing_rate": 1300.0,
    "utilization_target": 82.0,
    "actual_utilization": 76.3,
    "primary_specialization": "Security Architecture",
    "secondary_specialization": "Data Architecture",
    "industry_expertise": "Consumer Tech, HealthTech, Enterprise Software",
    "certifications": "Google Cloud Architect",
    "performance_score": 3.5,
    "client_satisfaction": 4.4,
    "internal_project_contribution": 2.0,
    "active_projects": 2.0,
    "project_complexity_score": 3.0,
    "delivery_quality_score": 80.9,
    "innovation_contribution": 4.7,
    "training_hours": 56.0,
    "mentorship_hours": -28.0,
    "promotion_readiness": 52.4,
    "flight_risk_score": 48.0,
    "engagement_score": 6.6,
    "knowledge_sharing_index": 2.7,
    "manager_id": 604201,
    "total_comp": 111100.00000000001,
    "team_lead_projects": 0.0,
    "direct_reports": 0.0
  },
  {
    "employee_id": 604201.0,
    "full_name": "Richard Aguirre",
    "department": "Product Architecture",
    "position": "Technical Director",
    "level": "senior",
    "hire_date": "2012-05-05",
    "city": "New York",
    "country": "USA",
    "region": "Americas",
    "remote_work_ratio": 0.8,
    "travel_percentage": 36.0,
    "base_salary": 273000.0,
    "billing_rate": 3100.0,
    "utilization_target": 67.0,
    "actual_utilization": 74.0,
    "primary_specialization": "Data Architecture",
    "secondary_specialization": "Security Architecture",
    "industry_expertise": "Consumer Tech, Social Impact",
    "certifications": "Azure Architect, AWS Solutions Architect, Google Cloud Architect",
    "performance_score": 4.1,
    "client_satisfaction": 4.1,
    "internal_project_contribution": 6.0,
    "active_projects": 4.0,
    "project_complexity_score": 4.0,
    "delivery_quality_score": 90.7,
    "innovation_contribution": 8.4,
    "training_hours": 25.0,
    "mentorship_hours": 21.0,
    "promotion_readiness": 7.432311707948527,
    "flight_risk_score": 48.0,
    "engagement_score": 8.5,
    "knowledge_sharing_index": 8.0,
    "manager_id": null,
    "total_comp": 327600.0,
    "team_lead_projects": 2.0,
    "direct_reports": 8.0
  },
  {
    "employee_id": 199659.0,
    "full_name": "Matthew Gomez",
    "department": "Engineering Delivery",
    "position": "Engineering Manager",
    "level": "senior",
    "hire_date": "2015-11-01",
    "city": "San Francisco",
    "country": "USA",
    "region": "Americas",
    "remote_work_ratio": 0.88,
    "travel_percentage": 21.0,
    "base_salary": 254000.0,
    "billing_rate": 2300.0,
    "utilization_target": 71.0,
    "actual_utilization": 71.7,
    "primary_specialization": "Backend",
    "secondary_specialization": "Full Stack",
    "industry_expertise": "EdTech, E-commerce, Industrial Tech, Social Impact",
    "certifications": "Azure Developer, AWS Developer",
    "performance_score": 4.5,
    "client_satisfaction": 4.5,
    "internal_project_contribution": 5.0,
    "active_projects": 3.0,
    "project_complexity_score": 5.0,
    "delivery_quality_score": 93.6,
    "innovation_contribution": 9.3,
    "training_hours": 32.0,
    "mentorship_hours": 24.0,
    "promotion_readiness": 17.851236844547245,
    "flight_risk_score": 25.0,
    "engagement_score": 7.1,
    "knowledge_sharing_index": 7.8,
    "manager_id": null,
    "total_comp": 317500.0,
    "team_lead_projects": 2.0,
    "direct_reports": 1.0
  }
]